sixel/__init__.py
sixel/sixel.py
matplotlib_sixel-0.0.2.dist-info/LICENSE
matplotlib_sixel-0.0.2.dist-info/METADATA
matplotlib_sixel-0.0.2.dist-info/WHEEL
matplotlib_sixel-0.0.2.dist-info/top_level.txt
matplotlib_sixel-0.0.2.dist-info/RECORD
