Metadata-Version: 2.1
Name: matplotlib-sixel
Version: 0.0.2
Summary: Matplotlib backend for showing sixel graphics
Home-page: https://github.com/jonathf/matplotlib-sixel
Author: Jonathan Feinberg
Author-email: jonathf@gmail.com
License: UNKNOWN
Platform: UNKNOWN
License-File: LICENSE
